Metadata-Version: 1.1
Name: pycity
Version: 0.1.3
Summary: Provides programmatic access to a list of the largest US Cities
Home-page: https://github.com/jskopek/pycity
Author: Jean-Marc Skopek
Author-email: jskopek@gmail.com
License: UNKNOWN
Download-URL: https://github.com/jskopek/pycity/archive/0.1.3.tar.gz
Platform: UNKNOWN
